{"galleries": 
	[
		{	"id": 1, 
			"title": "Chilenitza", 
			"client": "LP Hoesontwerp", 
			"category": "Category: Identity & Web",
			"description": "This is a description",
			"autor": "Ac Berker / Isabelle Boon", 
			"gallery": [
				{
					"id": 1,
					"type": "single",
					"location": "assets/images/home/img.jpg",
					"color": "black"
				},
				{
					"id": 2,
					"type": "doble",
					"location": "assets/images/home/img.jpg",
					"color": "black"
				},
				{
					"id": 3,
					"type": "doble",
					"location": "assets/images/home/img.jpg",
					"color": "black"

				},
				{
					"id": 4,
					"type": "complex",
					"location": "assets/images/home/img.jpg",
					"inerImages":[
						{
							"id": 4,
							"location": "assets/images/home/img.jpg"
						},
						{
							"id":5,
							"location": "assets/images/home/img.jpg"
						}
					],
					"color": "black"
				},
				{
					"id": 6,
					"type": "single",
					"location": "assets/images/home/img.jpg",
					"color": "black"				
				},
				{
					"id": 7,
					"type": "doble",
					"location": "assets/images/home/img.jpg",
					"color": "black"
				},
				{
					"id": 8,
					"type": "doble",
					"location": "assets/images/home/img.jpg",
					"color": "black"
				},
				{
					"id": 9,
					"type": "single",
					"location": "assets/images/home/img.jpg",
					"color": "black"				
				},
				{
					"id": 10,
					"type": "complex",
					"location": "assets/images/home/img.jpg",
					"inerImages":[
						{
							"id": 10,
							"location": "assets/images/home/img.jpg"
						},
						{
							"id":11,
							"location": "assets/images/home/img.jpg"
						}
					],
					"color": "black"
				},
				{
					"id": 12,
					"type": "doble",
					"location": "assets/images/home/img.jpg",
					"color": "black"
				},
				{
					"id":13,
					"type": "doble",
					"location": "assets/images/home/img.jpg",
					"color": "black"
				},
				{
					"id": 14,
					"type": "single",
					"location": "assets/images/home/img.jpg",
					"color": "black"				
				}
			]
		},
		{	"id": 2, 
			"title": "Mezcal", 
			"client": "LP Hoesontwerp", 
			"category": "Category: Identity & Web",
			"description": "This is a description",
			"autor": "Ac Berker / Isabelle Boon", 
			"gallery": [
				{
					"id": 1,
					"type": "single",
					"location": "assets/images/home/img.jpg",
					"color": "yellow"
				},
				{
					"id": 2,
					"type": "doble",
					"location": "assets/images/home/img.jpg",
					"color": "yellow"
				},
				{
					"id": 3,
					"type": "doble",
					"location": "assets/images/home/img.jpg",
					"color": "yellow"

				},
				{
					"id": 4,
					"type": "complex",
					"location": "assets/images/home/img.jpg",
					"inerImages":[
						{
							"id": 4,
							"location": "assets/images/home/img.jpg"
						},
						{
							"id":5,
							"location": "assets/images/home/img.jpg"
						}
					],
					"color": "yellow"
				},
				{
					"id": 6,
					"type": "complex",
					"location": "assets/images/home/img.jpg",
					"inerImages":[
						{
							"id": 6,
							"location": "assets/images/home/img.jpg"
						},
						{
							"id": 7,
							"location": "assets/images/home/img.jpg"
						}
					],
					"color": "yellow"
				},
				{
					"id": 8,
					"type": "doble",
					"location": "assets/images/home/img.jpg",
					"color": "yellow"

				},
				{
					"id": 9,
					"type": "full",
					"location": "assets/images/home/img.jpg",
					"color": "yellow"

				},
				{
					"id": 10,
					"type": "complex",
					"location": "assets/images/home/img.jpg",
					"inerImages":[
						{
							"id": 10,
							"location": "assets/images/home/img.jpg"
						},
						{
							"id": 11,
							"location": "assets/images/home/img.jpg"
						}
					],
					"color": "yellow"
				},
				{
					"id": 12,
					"type": "doble",
					"location": "assets/images/home/img.jpg",
					"color": "yellow"

				},
				{
					"id": 13,
					"type": "doble",
					"location": "assets/images/home/img.jpg",
					"color": "yellow"

				},
				{
					"id": 14,
					"type": "single",
					"location": "assets/images/home/img.jpg",
					"color": "yellow"
				}
				
			]
		},
		{	"id": 3, 
			"title": "Bowker", 
			"client": "LP Hoesontwerp", 
			"category": "Category: Identity & Web",
			"description": "This is a description",
			"autor": "Ac Berker / Isabelle Boon", 
			"gallery": [
				{
					"id": 1,
					"type": "single",
					"location": "assets/images/home/img.jpg",
					"color": "blue"
				},
				{
					"id": 2,
					"type": "doble",
					"location": "assets/images/home/img.jpg",
					"color": "blue"
				},
				{
					"id": 3,
					"type": "complex",
					"location": "assets/images/home/img.jpg",
					"inerImages":[
						{
							"id": 3,
							"location": "assets/images/home/img.jpg"
						},
						{
							"id": 4,
							"location": "assets/images/home/img.jpg"
						}
					],
					"color": "blue"
				},
				{
					"id": 5,
					"type": "doble",
					"location": "assets/images/home/img.jpg",
					"color": "blue"
				},
				{
					"id": 6,
					"type": "complex",
					"location": "assets/images/home/img.jpg",
					"inerImages":[
						{
							"id": 6,
							"location": "assets/images/home/img.jpg"
						},
						{
							"id": 7,
							"location": "assets/images/home/img.jpg"
						}
					],
					"color": "blue"
				},
				{
					"id": 8,
					"type": "doble",
					"location": "assets/images/home/img.jpg",
					"color": "blue"
				}
			]
		},
		{	"id": 4, 
			"title": "Contador", 
			"client": "LP Hoesontwerp", 
			"category": "Category: Identity & Web",
			"description": "This is a description",
			"autor": "Ac Berker / Isabelle Boon", 
			"gallery": [
				{
					"id": 1,
					"type": "single",
					"location": "assets/images/home/img.jpg",
					"color": "yellow"
				},
				{
					"id": 2,
					"type": "doble",
					"location": "assets/images/home/img.jpg",
					"color": "yellow"
				},
				{
					"id": 4,
					"type": "complex",
					"location": "assets/images/home/img.jpg",
					"inerImages":[
						{
							"id": 3,
							"location": "assets/images/home/img.jpg"
						},
						{
							"id": 4,
							"location": "assets/images/home/img.jpg"
						}
					],
					"color": "yellow"
				},
				{
					"id": 5,
					"type": "doble",
					"location": "assets/images/home/img.jpg",
					"color": "yellow"
				},
				{
					"id": 6,
					"type": "complex",
					"location": "assets/images/home/img.jpg",
					"inerImages":[
						{
							"id": 6,
							"location": "assets/images/home/img.jpg"
						},
						{
							"id": 7,
							"location": "assets/images/home/img.jpg"
						}
					],
					"color": "yellow"
				},
				{
					"id": 8,
					"type": "doble",
					"location": "assets/images/home/img.jpg",
					"color": "yellow"
				}
			]
		}
	]
}









